fucknuker/__init__.py
fucknuker/main.py
fucknuker-0.1.1.dist-info/METADATA
fucknuker-0.1.1.dist-info/WHEEL
fucknuker-0.1.1.dist-info/entry_points.txt
fucknuker-0.1.1.dist-info/top_level.txt
fucknuker-0.1.1.dist-info/RECORD
